py3toolset/LICENSE.md
py3toolset/__init__.py
py3toolset/bash_autocomp.py
py3toolset/cmd_interact.py
py3toolset/dep.py
py3toolset/file_backup.py
py3toolset/fs.py
py3toolset/nmath.py
py3toolset/setup.py
py3toolset/tuple_file.py
py3toolset/txt_color.py
py3toolset-1.2.20.dist-info/licenses/LICENSE.md
py3toolset-1.2.20.dist-info/METADATA
py3toolset-1.2.20.dist-info/WHEEL
py3toolset-1.2.20.dist-info/top_level.txt
py3toolset-1.2.20.dist-info/RECORD
