Metadata-Version: 2.4
Name: py3toolset
Version: 1.2.20
Summary: Python utility modules.
Home-page: 
License: 3-clause BSD 2.0
Classifier: License :: OSI Approved :: BSD License
Classifier: Programming Language :: Python :: 3
Classifier: Topic :: Software Development
License-File: LICENSE.md
Requires-Dist: numpy>=2
Dynamic: classifier
Dynamic: description
Dynamic: description-content-type
Dynamic: license
Dynamic: license-file
Dynamic: requires-dist
Dynamic: summary
